LICENSE
MANIFEST.in
README.md
requirements.txt
setup.cfg
setup.py
articles/__init__.py
articles/admin.py
articles/config.py
articles/defaults.py
articles/models.py
articles/settings.py
articles/translation.py
articles/urls.py
articles/views.py
articles/locale/fr/LC_MESSAGES/django.mo
articles/locale/fr/LC_MESSAGES/django.po
articles/locale/nl/LC_MESSAGES/django.mo
articles/locale/nl/LC_MESSAGES/django.po
articles/locale/ru/LC_MESSAGES/django.mo
articles/locale/ru/LC_MESSAGES/django.po
articles/locale/uk/LC_MESSAGES/django.mo
articles/locale/uk/LC_MESSAGES/django.po
articles/migrations/0001_initial.py
articles/migrations/__init__.py
articles/templates/articles/detail.html
articles/templates/articles/list.html
articles/templates/articles/admin/preview.html
articles/templatetags/__init__.py
articles/templatetags/articles.py
django_mp_articles.egg-info/PKG-INFO
django_mp_articles.egg-info/SOURCES.txt
django_mp_articles.egg-info/dependency_links.txt
django_mp_articles.egg-info/requires.txt
django_mp_articles.egg-info/top_level.txt