Metadata-Version: 2.1
Name: django-mp-articles
Version: 9.2.1
Summary: Django articles apps
Home-page: https://github.com/pmaigutyak/mp-articles
Author: Paul Maigutyak
Author-email: pmaigutyak@gmail.com
License: MIT
Download-URL: https://github.com/pmaigutyak/mp-articles/archive/9.2.1.tar.gz
Platform: UNKNOWN
License-File: LICENSE
